pact_ffi/ffi.pyd
pact_ffi/ffi.pyi
pact_ffi/pact_ffi.dll
pact_ffi/pact_ffi.lib
pact_ffi/py.typed
pact_ffi/__init__.py
pact_ffi/__version__.py
pact_python_ffi-0.4.28.1.dist-info/DELVEWHEEL
pact_python_ffi-0.4.28.1.dist-info/METADATA
pact_python_ffi-0.4.28.1.dist-info/RECORD
pact_python_ffi-0.4.28.1.dist-info/WHEEL
pact_python_ffi-0.4.28.1.dist-info/licenses/LICENSE
pact_python_ffi.libs/.load-order-pact_python_ffi-0.4.28.1
pact_python_ffi.libs/pact_ffi-47ec00026ab65e19bed047a28bb122fc.dll
