Metadata-Version: 2.4
Name: pact-python-ffi
Version: 0.4.28.1
Summary: Python bindings for the Pact FFI library
Project-URL: Bug Tracker, https://github.com/pact-foundation/pact-python/issues
Project-URL: Changelog, https://github.com/pact-foundation/pact-python/blob/main/pact-python-ffi/CHANGELOG.md
Project-URL: Documentation, https://docs.pact.io
Project-URL: Homepage, https://pact.io
Project-URL: Repository, https://github.com/pact-foundation/pact-python
Author-email: Joshua Ellis <josh@jpellis.me>
Maintainer-email: Joshua Ellis <josh@jpellis.me>
License-Expression: MIT
License-File: LICENSE
Keywords: contract-testing,ffi,pact,pact-python
Classifier: Development Status :: 5 - Production/Stable
Classifier: Environment :: Console
Classifier: Intended Audience :: Developers
Classifier: License :: OSI Approved :: MIT License
Classifier: Operating System :: MacOS :: MacOS X
Classifier: Operating System :: Microsoft :: Windows
Classifier: Operating System :: POSIX :: Linux
Classifier: Programming Language :: Python
Classifier: Programming Language :: Python :: 3 :: Only
Classifier: Programming Language :: Python :: 3.9
Classifier: Programming Language :: Python :: 3.10
Classifier: Programming Language :: Python :: 3.11
Classifier: Programming Language :: Python :: 3.12
Classifier: Programming Language :: Python :: 3.13
Classifier: Topic :: Software Development :: Testing
Requires-Python: >=3.9
Requires-Dist: cffi~=1.0
